babel_utils.py
babel_utils-0.1.0.post2.dist-info/LICENSE
babel_utils-0.1.0.post2.dist-info/METADATA
babel_utils-0.1.0.post2.dist-info/WHEEL
babel_utils-0.1.0.post2.dist-info/top_level.txt
babel_utils-0.1.0.post2.dist-info/RECORD
