Metadata-Version: 2.1
Name: babel-utils
Version: 0.1.0.post2
Summary: WARNING: This package has been renamed to bpc-utils!
Home-page: https://github.com/pybpc/bpc-utils
Author: Saiyang Gou
Author-email: gousaiyang223@gmail.com
License: MIT
Platform: UNKNOWN
Classifier: Development Status :: 5 - Production/Stable
Classifier: Intended Audience :: Developers
Classifier: Intended Audience :: Information Technology
Classifier: License :: OSI Approved :: MIT License
Classifier: Operating System :: OS Independent
Classifier: Programming Language :: Python :: 3 :: Only
Classifier: Topic :: Software Development
Classifier: Topic :: Utilities
Requires-Python: >=3
